banner_j25ng/__init__.py
banner_j25ng/banner.py
banner_j25ng-0.3.1.dist-info/METADATA
banner_j25ng-0.3.1.dist-info/WHEEL
banner_j25ng-0.3.1.dist-info/entry_points.txt
banner_j25ng-0.3.1.dist-info/top_level.txt
banner_j25ng-0.3.1.dist-info/RECORD
