Metadata-Version: 2.1
Name: banner_j25ng
Version: 0.3.1
Summary: Banner Output Program
Author-email: j25ng <jsan2861@gmail.com>
License: MIT
Project-URL: Homepage, https://github.com/j25ng/banner_j25ng
Project-URL: Issues, https://github.com/j25ng/banner_j25ng/issues
Requires-Python: >=3.9
Requires-Dist: pyfiglet >=1.0.2
